midplot/nothing.py
midplot-0.0.2.dist-info/LICENSE
midplot-0.0.2.dist-info/METADATA
midplot-0.0.2.dist-info/WHEEL
midplot-0.0.2.dist-info/entry_points.txt
midplot-0.0.2.dist-info/top_level.txt
midplot-0.0.2.dist-info/RECORD
